caerp_sign_pdf/__init__.py
caerp_sign_pdf/models.py
caerp_sign_pdf/public.py
caerp_sign_pdf-2024.2.2.dist-info/LICENSE.txt
caerp_sign_pdf-2024.2.2.dist-info/METADATA
caerp_sign_pdf-2024.2.2.dist-info/WHEEL
caerp_sign_pdf-2024.2.2.dist-info/top_level.txt
caerp_sign_pdf-2024.2.2.dist-info/RECORD
