Metadata-Version: 2.2
Name: caerp_sign_pdf
Version: 2024.2.2
Summary: caerp_sign_pdf
Home-page: https://framagit.org/caerp/caerp_sign_pdf
Author: Kilya
Author-email: contact@kilya.net
License: GPLv3
Keywords: web wsgi bfg pylons pyramid caerp
Classifier: License :: OSI Approved :: GNU General Public License v3 (GPLv3)
Classifier: Programming Language :: Python
Classifier: Framework :: Pyramid
Classifier: Topic :: Internet :: WWW/HTTP
Classifier: Topic :: Internet :: WWW/HTTP :: WSGI :: Application
License-File: LICENSE.txt
Requires-Dist: pyHanko[image-support,opentype,pkcs11,xmp]==0.25.1
Dynamic: author
Dynamic: author-email
Dynamic: classifier
Dynamic: description
Dynamic: description-content-type
Dynamic: home-page
Dynamic: keywords
Dynamic: license
Dynamic: requires-dist
Dynamic: summary
